faker_geoscience/__init__.py
faker_geoscience/flora/__init__.py
faker_geoscience/flora/el_GR/__init__.py
faker_geoscience/geography/__init__.py
faker_geoscience/geography/el_GR/__init__.py
faker_geoscience/minerals/__init__.py
faker_geoscience/minerals/el_GR/__init__.py
faker_geoscience-0.1.0.dist-info/LICENSE
faker_geoscience-0.1.0.dist-info/METADATA
faker_geoscience-0.1.0.dist-info/WHEEL
faker_geoscience-0.1.0.dist-info/top_level.txt
faker_geoscience-0.1.0.dist-info/RECORD
