Metadata-Version: 2.1
Name: faker-geoscience
Version: 0.1.0
Summary: Faker addon with providers for everything Earth!
Author: tplessas, e-panourgia
License: AGPL-3.0 license
Project-URL: homepage, https://github.com/tplessas/faker-geoscience
Keywords: faker,geoscience,data,generator,earth
Classifier: Intended Audience :: Developers
Classifier: Programming Language :: Python
Classifier: Topic :: Software Development :: Libraries :: Python Modules
Classifier: Topic :: Software Development :: Testing
Classifier: Topic :: Utilities
Classifier: License :: OSI Approved :: GNU Affero General Public License v3
Requires-Python: >=3.6
License-File: LICENSE
Requires-Dist: faker
